{"name":"Customer place an order by purchasing an item from search","id":"automated-end2end-tests;customer-place-an-order-by-purchasing-an-item-from-search","testSteps":[{"number":1,"description":"Given user is on Home Page","duration":2723,"startTime":"2018-11-01T13:31:06.555+02:00[Europe/Kiev]","result":"SUCCESS","precondition":false},{"number":2,"description":"When he enter \"https://www.gmail.com\" site","duration":4258,"startTime":"2018-11-01T13:31:09.281+02:00[Europe/Kiev]","result":"SUCCESS","precondition":false},{"number":3,"description":"When the user press the Log-in button","duration":1361,"startTime":"2018-11-01T13:31:13.540+02:00[Europe/Kiev]","result":"SUCCESS","precondition":false},{"number":4,"description":"And enter an email address \"kunata1109@gmail.com\"","duration":175,"startTime":"2018-11-01T13:31:14.902+02:00[Europe/Kiev]","result":"SUCCESS","precondition":false},{"number":5,"description":"And press the Next button","duration":113,"startTime":"2018-11-01T13:31:15.077+02:00[Europe/Kiev]","result":"SUCCESS","precondition":false},{"number":6,"description":"And enter the password \"Secret_123\"","duration":1094,"startTime":"2018-11-01T13:31:15.191+02:00[Europe/Kiev]","result":"SUCCESS","precondition":false},{"number":7,"description":"And press the Next button","duration":92,"startTime":"2018-11-01T13:31:16.285+02:00[Europe/Kiev]","result":"SUCCESS","precondition":false}],"userStory":{"id":"automated-end2end-tests","storyName":"Automated End2End Tests","path":"src/test/java/functionalTests/End2End_Tests.feature","narrative":"  Description: The purpose of this feature is to tests End 2 End integration","type":"feature"},"featureTag":{"name":"Functional tests/Automated End2End Tests","type":"feature"},"title":"Customer place an order by purchasing an item from search","startTime":"2018-11-01T13:31:06.338+02:00[Europe/Kiev]","duration":10040,"projectKey":"","manual":false,"testSource":"Cucumber","result":"SUCCESS"}